imdb/__init__.py
imdb/__main__.py
imdb/api.py
imdb/imdb.py
tdm_percy-0.1.1.dist-info/LICENSE
tdm_percy-0.1.1.dist-info/METADATA
tdm_percy-0.1.1.dist-info/WHEEL
tdm_percy-0.1.1.dist-info/entry_points.txt
tdm_percy-0.1.1.dist-info/top_level.txt
tdm_percy-0.1.1.dist-info/RECORD
